ebay_find_completed/__init__.py
ebay_find_completed/element.py
ebay_find_completed/helpers.py
ebay_find_completed/scraper.py
ebay_find_completed-0.0.8.dist-info/LICENSE
ebay_find_completed-0.0.8.dist-info/METADATA
ebay_find_completed-0.0.8.dist-info/WHEEL
ebay_find_completed-0.0.8.dist-info/top_level.txt
ebay_find_completed-0.0.8.dist-info/RECORD
