Metadata-Version: 2.1
Name: ebay-find-completed
Version: 0.0.8
Summary: eBay removed the very useful `findCompletedItems` endpoint from their api. Now we have to scrape their website. 😒
Home-page: https://github.com/willmeyers/ebay-find-completed
Author: Will Meyers
License: UNKNOWN
Platform: UNKNOWN
Classifier: Programming Language :: Python :: 3
Classifier: License :: OSI Approved :: MIT License
Classifier: Operating System :: OS Independent
Requires-Python: >=3.8
Requires-Dist: pyppeteer
Requires-Dist: lxml
